README.rst
setup.py
pykl/__init__.py
pykl/pyfile.py
pykl/pyhtml.py
pykl/pyhttp.py
pykl/pyjson.py
pykl/pylext.py
pykl/pyutils.py
pykl/pyvaild.py
pykl.egg-info/PKG-INFO
pykl.egg-info/SOURCES.txt
pykl.egg-info/dependency_links.txt
pykl.egg-info/requires.txt
pykl.egg-info/top_level.txt
pykl/gdom/__init__.py
pykl/gdom/cmd.py
pykl/gdom/gpage.py
pykl/gdom/gredis.py
pykl/gdom/schema.py
pykl/tiny/__init__.py
pykl/tiny/func.py
pykl/tiny/codegen/__init__.py
pykl/tiny/codegen/codebuild.py
pykl/tiny/codegen/utils.py
pykl/tiny/dumptable/__init__.py
pykl/tiny/dumptable/codegen.py
pykl/tiny/grapheneinfo/__init__.py
pykl/tiny/grapheneinfo/converter.py
pykl/tiny/grapheneinfo/registry.py
pykl/tiny/grapheneinfo/types.py
pykl/tiny/grapheneinfo/utils.py