Metadata-Version: 1.0
Name: pykl
Version: 0.1.5
Summary: kltool for python, toolset for web, http, cache, dht, xml, json and so on
Home-page: http://github.com/wowngasb/pykl
Author: pykl
Author-email: me@wowngasb.com
License: MIT
Keywords: kltool html graphql xml json
Platform: UNKNOWN
